{
  "parent": "minecraft:recipes/root",
  "rewards": {
    "recipes": [
      "allomancy:steel_pattern"
    ]
  },
  "criteria": {
    "has_steel_flakes": {
      "trigger": "minecraft:inventory_changed",
      "conditions": {
        "items": [
          {
            "item": "allomancy:steel_flakes"
          }
        ]
      }
    },
    "has_the_recipe": {
      "trigger": "minecraft:recipe_unlocked",
      "conditions": {
        "recipe": "allomancy:steel_pattern"
      }
    }
  },
  "requirements": [
    [
      "has_steel_flakes",
      "has_the_recipe"
    ]
  ]
}